article_rec_db/__init__.py
article_rec_db/models/__init__.py
article_rec_db/models/article.py
article_rec_db/models/embedding.py
article_rec_db/models/helpers.py
article_rec_db/models/page.py
article_rec_db/models/recommendation.py
article_rec_db/models/recommender.py
article_rec_db/py.typed
article_rec_db-0.0.11.dist-info/LICENSE
article_rec_db-0.0.11.dist-info/METADATA
article_rec_db-0.0.11.dist-info/WHEEL
article_rec_db-0.0.11.dist-info/RECORD
