Metadata-Version: 2.1
Name: article-rec-db
Version: 0.0.11
Summary: Database models and migrations for the Local News Lab's article recommendation system
Home-page: https://github.com/LocalAtBrown/article-rec-db/
License: MIT
Author: Duy Nguyen
Author-email: hello.duyknguyen@gmail.com
Requires-Python: >=3.9,<3.12
Classifier: License :: OSI Approved :: MIT License
Classifier: Programming Language :: Python :: 3
Classifier: Programming Language :: Python :: 3.9
Classifier: Programming Language :: Python :: 3.10
Classifier: Programming Language :: Python :: 3.11
Requires-Dist: numpy (>=1.26.1,<2.0.0)
Requires-Dist: pgvector (>=0.2.3,<0.3.0)
Requires-Dist: psycopg2 (>=2.9.9,<3.0.0)
Requires-Dist: pydantic (>=2.5.0,<3.0.0)
Requires-Dist: sqlalchemy (>=2.0.0,<3.0.0)
Requires-Dist: sqlmodel (>=0.0.14,<0.0.15)
Project-URL: Documentation, https://github.com/LocalAtBrown/article-rec-db/
Project-URL: Repository, https://github.com/LocalAtBrown/article-rec-db/
